{
  "$schema": "https://json-schema.org/draft/2020-12/schema",
  "$id": "https://efl.dev/schemas/efl-manifest.schema.json",
  "title": "EFL Manifest",
  "description": "Schema for .efl capability manifest files",
  "type": "object",
  "required": ["schemaVersion", "modId", "name", "version", "eflVersion"],
  "properties": {
    "schemaVersion": {
      "type": "integer",
      "description": "Manifest schema version"
    },
    "modId": {
      "type": "string",
      "description": "Unique mod identifier (reverse domain notation)"
    },
    "name": {
      "type": "string",
      "description": "Human-readable mod name"
    },
    "version": {
      "type": "string",
      "description": "Mod version (semver)"
    },
    "eflVersion": {
      "type": "string",
      "description": "Minimum required EFL version (semver)"
    },
    "requiredDeps": {
      "type": "array",
      "description": "Mods that must be present for this mod to load",
      "items": {
        "type": "object",
        "required": ["modId", "versionRange"],
        "properties": {
          "modId":        { "type": "string", "description": "Dependency mod ID (reverse domain notation)" },
          "versionRange": { "type": "string", "description": "Semver range, e.g. \"^1.0\"" }
        }
      }
    },
    "optionalDeps": {
      "type": "array",
      "description": "Mods that enhance this mod if present but are not required",
      "items": {
        "type": "object",
        "required": ["modId", "versionRange"],
        "properties": {
          "modId":        { "type": "string" },
          "versionRange": { "type": "string" }
        }
      }
    },
    "features": {
      "type": "object",
      "description": "Feature flags declaring which EFL subsystems this mod uses",
      "properties": {
        "areas": { "type": "boolean" },
        "warps": { "type": "boolean" },
        "resources": { "type": "boolean" },
        "crafting": { "type": "boolean" },
        "npcs": { "type": "boolean" },
        "quests": { "type": "boolean" },
        "triggers": { "type": "boolean" },
        "dialogue": { "type": "boolean" },
        "story": { "type": "boolean" },
        "ipcPublish": { "type": "boolean" },
        "ipcConsume": { "type": "boolean" },
        "migrations": { "type": "boolean" }
      }
    },
    "settings": {
      "type": "object",
      "properties": {
        "strictMode": { "type": "boolean" },
        "areaBackend": { "type": "string" },
        "saveScope": { "type": "string" }
      }
    },
    "scriptHooks": {
      "type": "array",
      "description": "Script hooks declared by this mod (v2.2). Default mode is 'callback' (built-in EFL handler). Use mode 'inject' to opt into future GML injection support.",
      "items": {
        "type": "object",
        "required": ["target", "handler"],
        "properties": {
          "target":  { "type": "string", "description": "GML script name to hook, e.g. gml_Script_hoe_node" },
          "handler": { "type": "string", "description": "Built-in EFL handler name, e.g. efl_resource_despawn" },
          "mode":    { "type": "string", "enum": ["callback", "inject"], "default": "callback" }
        }
      }
    }
  }
}
